dtree.py
dtree_python-1.0.5.dist-info/LICENSE
dtree_python-1.0.5.dist-info/METADATA
dtree_python-1.0.5.dist-info/WHEEL
dtree_python-1.0.5.dist-info/top_level.txt
dtree_python-1.0.5.dist-info/RECORD
